naughtty/__init__.py
naughtty/__main__.py
naughtty/cli.py
naughtty/constants.py
naughtty/naughtty.py
naughtty/py.typed
naughtty/version/VERSION
naughtty/version/__init__.py
naughtty/version/py.typed
naughtty-1.0.1.dist-info/LICENSE
naughtty-1.0.1.dist-info/METADATA
naughtty-1.0.1.dist-info/WHEEL
naughtty-1.0.1.dist-info/entry_points.txt
naughtty-1.0.1.dist-info/top_level.txt
naughtty-1.0.1.dist-info/RECORD
