Metadata-Version: 2.1
Name: naughtty
Version: 1.0.1
Summary: Python package and CLI tool for executing shell commands in a pseudo-terminal
Home-page: https://github.com/cariad/naughtty
Author: Cariad Eccleston
Author-email: cariad@cariad.io
License: MIT
Platform: UNKNOWN
Classifier: Development Status :: 5 - Production/Stable
Classifier: Environment :: Console
Classifier: License :: OSI Approved :: MIT License
Classifier: Natural Language :: English
Classifier: Operating System :: POSIX :: Linux
Classifier: Programming Language :: Python :: 3 :: Only
Classifier: Programming Language :: Python :: 3.8
Classifier: Programming Language :: Python :: 3.9
Classifier: Topic :: Utilities
Classifier: Typing :: Typed
Requires-Python: >=3.8
License-File: LICENSE
